parenx/__init__.py
parenx/parenx
parenx/run.sh
parenx/shared.py
parenx/skeletonize.py
parenx/tile_skeletonize.py
parenx/voronoi.py
parenx/data/rnet_doncaster_rail.geojson
parenx/data/rnet_princes_street.geojson
parenx-0.7.5.1.dist-info/licenses/LICENSE
parenx-0.7.5.1.dist-info/METADATA
parenx-0.7.5.1.dist-info/WHEEL
parenx-0.7.5.1.dist-info/entry_points.txt
parenx-0.7.5.1.dist-info/top_level.txt
parenx-0.7.5.1.dist-info/RECORD
