Metadata-Version: 2.4
Name: parenx
Version: 0.7.5.1
Summary: GeoJSON network simplification using raster image skeletonization and Voronoi polygons
Author-email: Will Deakin <will.deakin@crinstitute.org.uk>
Project-URL: Homepage, https://github.com/anisotropi4/parenx
Project-URL: Issues, https://github.com/anisotropi4/parenx/issues
Classifier: Programming Language :: Python :: 3
Classifier: Development Status :: 4 - Beta
Classifier: License :: OSI Approved :: Apache Software License
Classifier: Operating System :: OS Independent
Requires-Python: >=3.8
License-File: LICENSE
Requires-Dist: geopandas
Requires-Dist: pyogrio
Requires-Dist: rasterio
Requires-Dist: shapely
Requires-Dist: scikit-image
Dynamic: license-file
